LICENSE
MANIFEST.in
README.md
setup.py
Django_EMS_R25.egg-info/PKG-INFO
Django_EMS_R25.egg-info/SOURCES.txt
Django_EMS_R25.egg-info/dependency_links.txt
Django_EMS_R25.egg-info/requires.txt
Django_EMS_R25.egg-info/top_level.txt
ems_r25/VERSION
ems_r25/__init__.py
ems_r25/more_r25.py
ems_r25/tests.py
ems_r25/utils.py
ems_r25/management/__init__.py
ems_r25/management/commands/__init__.py
ems_r25/management/commands/ems2r25.py
ems_r25/resources/ems/file/ServiceSoap/GetAllRooms/58B9D6D0D1CD6AD798E4D04E5C1BEC8B
ems_r25/resources/ems/file/ServiceSoap/GetBookings/9F910892F967646F7B82D97EC498D4DB
ems_r25/resources/gws/file/group_sws/v2/group/u_classrm_services_ems_schedulers/effective_member/javerage
ems_r25/resources/gws/file/group_sws/v3/group/u_classrm_services_ems_schedulers/effective_member/javerage
ems_r25/resources/r25/file/r25ws/servlet/wrd/run/reservations.xml_scope_extended_space_query_id_999_start_dt_2018-12-18_end_dt_2018-12-18
ems_r25/resources/r25/file/r25ws/servlet/wrd/run/space_search.xml_query_id_999