Metadata-Version: 2.1
Name: Django-EMS-R25
Version: 1.5
Summary: Django app generate R25 events from EMS
Home-page: https://github.com/uw-it-cte/django-ems-r25
License: Apache License, Version 2.0
Platform: UNKNOWN
Classifier: Environment :: Web Environment
Classifier: Framework :: Django
Classifier: Intended Audience :: Developers
Classifier: License :: OSI Approved :: Apache Software License
Classifier: Operating System :: OS Independent
Classifier: Programming Language :: Python
Classifier: Programming Language :: Python :: 2.7
Classifier: Programming Language :: Python :: 3.6
License-File: LICENSE
